meowbit/SerialCom.py
meowbit/__init__.py
meowbit/font_12x16.bin
meowbit/meowbit.py
meowbit/pyboard.py
meowbit-0.1.9.dist-info/LICENSE
meowbit-0.1.9.dist-info/METADATA
meowbit-0.1.9.dist-info/WHEEL
meowbit-0.1.9.dist-info/top_level.txt
meowbit-0.1.9.dist-info/RECORD
