Metadata-Version: 2.1
Name: meowbit
Version: 0.1.9
Summary: Lib for meowbit, build over ampy from adafruit
Home-page: https://gitee.com/KittenTech/pylib_meowcode
Author: riven
Author-email: riven@kittenbot.cc
License: MIT
Keywords: meowbit
Platform: UNKNOWN
Requires-Dist: pyserial
Requires-Dist: pyusb
